{
  "jsonData": [
    {
      "담보명": "상해후유장해(3~100%)",
      "가입금액": "1000",
      "메리츠화재": 0,
      "농협손해": 661,
      "삼성화재": 560,
      "롯데손해보험": 370,
      "현대해상화재": 520,
      "흥국화재": 650,
      "DB손해보험": 800,
      "KB손해보험": 600,
      "하나손해": 590,
      "한화손해보험": 660
    },
    {
      "담보명": "상해고도후유(80%이상)",
      "가입금액": "1000",
      "메리츠화재": 98,
      "농협손해": 105,
      "삼성화재": 120,
      "롯데손해보험": 0,
      "현대해상화재": 85,
      "흥국화재": 110,
      "DB손해보험": 120,
      "KB손해보험": 100,
      "하나손해": 90,
      "한화손해보험": 110
    },
    {
      "담보명": "상해사망",
      "가입금액": "1000",
      "메리츠화재": 740,
      "농협손해": 900,
      "삼성화재": 990,
      "롯데손해보험": 600,
      "현대해상화재": 485,
      "흥국화재": 760,
      "DB손해보험": 1010,
      "KB손해보험": 880,
      "하나손해": 730,
      "한화손해보험": 790
    },
    {
      "담보명": "질병후유장해(3~100%)",
      "가입금액": "1000",
      "메리츠화재": 0,
      "농협손해": 40903,
      "삼성화재": 37800,
      "롯데손해보험": 32100,
      "현대해상화재": 30980,
      "흥국화재": 33110,
      "DB손해보험": 72330,
      "KB손해보험": 37560,
      "하나손해": 39420,
      "한화손해보험": 54490
    },
    {
      "담보명": "질병고도후유(80%이상)",
      "가입금액": "1000",
      "메리츠화재": 2220,
      "농협손해": 3778,
      "삼성화재": 2500,
      "롯데손해보험": 0,
      "현대해상화재": 3439,
      "흥국화재": 2710,
      "DB손해보험": 2700,
      "KB손해보험": 2770,
      "하나손해": 5040,
      "한화손해보험": 3775
    },
    {
      "담보명": "질병사망",
      "가입금액": "1000",
      "메리츠화재": 11140,
      "농협손해": 15113,
      "삼성화재": 12110,
      "롯데손해보험": 9990,
      "현대해상화재": 13769,
      "흥국화재": 12200,
      "DB손해보험": 21840,
      "KB손해보험": 12440,
      "하나손해": 11680,
      "한화손해보험": 15090
    },
    {
      "담보명": "가족일상생활중배상책임",
      "가입금액": "10000",
      "메리츠화재": 2078,
      "농협손해": 0,
      "삼성화재": 2877,
      "롯데손해보험": 2158,
      "현대해상화재": 2718,
      "흥국화재": 778,
      "DB손해보험": 1283,
      "KB손해보험": 3099,
      "하나손해": 0,
      "한화손해보험": 1818
    },
    {
      "담보명": "통합암진단비",
      "가입금액": "1000",
      "메리츠화재": 29120,
      "농협손해": 44184,
      "삼성화재": 47540,
      "롯데손해보험": 23460,
      "현대해상화재": 51030,
      "흥국화재": 34880,
      "DB손해보험": 37150,
      "KB손해보험": 32830,
      "하나손해": 36400,
      "한화손해보험": 44880
    },
    {
      "담보명": "암진단비(유사암제외)",
      "가입금액": "3000",
      "메리츠화재": 67170,
      "농협손해": 69780,
      "삼성화재": 77220,
      "롯데손해보험": 58230,
      "현대해상화재": 67230,
      "흥국화재": 59220,
      "DB손해보험": 73680,
      "KB손해보험": 64920,
      "하나손해": 70590,
      "한화손해보험": 72900
    },
    {
      "담보명": "특정암진단비",
      "가입금액": "500",
      "메리츠화재": 6480,
      "농협손해": 0,
      "삼성화재": 7040,
      "롯데손해보험": 0,
      "현대해상화재": 6000,
      "흥국화재": 5420,
      "DB손해보험": 7155,
      "KB손해보험": 6275,
      "하나손해": 7120,
      "한화손해보험": 0
    },
    {
      "담보명": "고액암진단비",
      "가입금액": "1000",
      "메리츠화재": 3630,
      "농협손해": 3750,
      "삼성화재": 0,
      "롯데손해보험": 0,
      "현대해상화재": 0,
      "흥국화재": 0,
      "DB손해보험": 4660,
      "KB손해보험": 1920,
      "하나손해": 3580,
      "한화손해보험": 0
    },
    {
      "담보명": "유사암진단비",
      "가입금액": "1000",
      "메리츠화재": 2170,
      "농협손해": 2190,
      "삼성화재": 3900,
      "롯데손해보험": 1950,
      "현대해상화재": 3580,
      "흥국화재": 2400,
      "DB손해보험": 3200,
      "KB손해보험": 2000,
      "하나손해": 2700,
      "한화손해보험": 3580
    },
    {
      "담보명": "재진단암진단비",
      "가입금액": "1000",
      "메리츠화재": 0,
      "농협손해": 0,
      "삼성화재": 0,
      "롯데손해보험": 0,
      "현대해상화재": 42880,
      "흥국화재": 0,
      "DB손해보험": 40080,
      "KB손해보험": 44680,
      "하나손해": 52850,
      "한화손해보험": 0
    },
    {
      "담보명": "암수술비(1회,유사암제외)",
      "가입금액": "500",
      "메리츠화재": 0,
      "농협손해": 0,
      "삼성화재": 11150,
      "롯데손해보험": 8000,
      "현대해상화재": 0,
      "흥국화재": 10900,
      "DB손해보험": 10775,
      "KB손해보험": 8770,
      "하나손해": 0,
      "한화손해보험": 7850
    },
    {
      "담보명": "암수술비(매회,유사암포함)",
      "가입금액": "300",
      "메리츠화재": 5646,
      "농협손해": 10374,
      "삼성화재": 11340,
      "롯데손해보험": 6762,
      "현대해상화재": 8700,
      "흥국화재": 10266,
      "DB손해보험": 10020,
      "KB손해보험": 7896,
      "하나손해": 7698,
      "한화손해보험": 9174
    },
    {
      "담보명": "암직접치료입원일당(1-180,요양병원제외)",
      "가입금액": "2",
      "메리츠화재": 2780,
      "농협손해": 3882,
      "삼성화재": 4030,
      "롯데손해보험": 1816,
      "현대해상화재": 3384,
      "흥국화재": 2716,
      "DB손해보험": 3280,
      "KB손해보험": 2198,
      "하나손해": 2678,
      "한화손해보험": 3086
    },
    {
      "담보명": "암요양병원입원비(1~90)",
      "가입금액": "1",
      "메리츠화재": 408,
      "농협손해": 596,
      "삼성화재": 596,
      "롯데손해보험": 253,
      "현대해상화재": 473,
      "흥국화재": 354,
      "DB손해보험": 458,
      "KB손해보험": 288,
      "하나손해": 593,
      "한화손해보험": 581
    },
    {
      "담보명": "다빈치로봇암수술비",
      "가입금액": "1000",
      "메리츠화재": 2340,
      "농협손해": 1460,
      "삼성화재": 2310,
      "롯데손해보험": 1030,
      "현대해상화재": 1485,
      "흥국화재": 1345,
      "DB손해보험": 3260,
      "KB손해보험": 1165,
      "하나손해": 1475,
      "한화손해보험": 586
    },
    {
      "담보명": "항암방사선약물치료비(최초1회한)",
      "가입금액": "300",
      "메리츠화재": 3279,
      "농협손해": 4362,
      "삼성화재": 6567,
      "롯데손해보험": 2556,
      "현대해상화재": 5790,
      "흥국화재": 2400,
      "DB손해보험": 3501,
      "KB손해보험": 4734,
      "하나손해": 2952,
      "한화손해보험": 5685
    },
    {
      "담보명": "표적항암약물허가치료비(최초1회한)",
      "가입금액": "1000",
      "메리츠화재": 1580,
      "농협손해": 1020,
      "삼성화재": 1700,
      "롯데손해보험": 1371,
      "현대해상화재": 1686,
      "흥국화재": 530,
      "DB손해보험": 1410,
      "KB손해보험": 5463,
      "하나손해": 1424,
      "한화손해보험": 740
    },
    {
      "담보명": "카티(CAR-T)항암약물허가치료비",
      "가입금액": "1000",
      "메리츠화재": 0,
      "농협손해": 0,
      "삼성화재": 0,
      "롯데손해보험": 22,
      "현대해상화재": 110,
      "흥국화재": 210,
      "DB손해보험": 0,
      "KB손해보험": 103,
      "하나손해": 16,
      "한화손해보험": 11
    },
    {
      "담보명": "암직접치료통원일당",
      "가입금액": "2",
      "메리츠화재": 0,
      "농협손해": 3456,
      "삼성화재": 3106,
      "롯데손해보험": 5162,
      "현대해상화재": 0,
      "흥국화재": 0,
      "DB손해보험": 5928,
      "KB손해보험": 8900,
      "하나손해": 1654,
      "한화손해보험": 2486
    },
    {
      "담보명": "암직접치료통원일당(상급종합병원)",
      "가입금액": "10",
      "메리츠화재": 11840,
      "농협손해": 11510,
      "삼성화재": 9180,
      "롯데손해보험": 7750,
      "현대해상화재": 9530,
      "흥국화재": 6370,
      "DB손해보험": 8790,
      "KB손해보험": 13620,
      "하나손해": 10530,
      "한화손해보험": 8240
    },
    {
      "담보명": "암주요치료비(5년)",
      "가입금액": "1000",
      "메리츠화재": 0,
      "농협손해": 0,
      "삼성화재": 0,
      "롯데손해보험": 0,
      "현대해상화재": 0,
      "흥국화재": 0,
      "DB손해보험": 0,
      "KB손해보험": 0,
      "하나손해": 0,
      "한화손해보험": 0
    },
    {
      "담보명": "암주요치료비(10년)",
      "가입금액": "1000",
      "메리츠화재": 33928,
      "농협손해": 38753,
      "삼성화재": 36278,
      "롯데손해보험": 36152,
      "현대해상화재": 34930,
      "흥국화재": 34210,
      "DB손해보험": 37284,
      "KB손해보험": 51358,
      "하나손해": 35364,
      "한화손해보험": 44640
    },
    {
      "담보명": "암상급종합병원주요치료비(10년)",
      "가입금액": "1000",
      "메리츠화재": 22472,
      "농협손해": 26365,
      "삼성화재": 26888,
      "롯데손해보험": 23772,
      "현대해상화재": 25166,
      "흥국화재": 22530,
      "DB손해보험": 23832,
      "KB손해보험": 33546,
      "하나손해": 23022,
      "한화손해보험": 27698
    },
    {
      "담보명": "하이클래스암주요치료비",
      "가입금액": "1000",
      "메리츠화재": 5580,
      "농협손해": 6301,
      "삼성화재": 6450,
      "롯데손해보험": 5130,
      "현대해상화재": 5954,
      "흥국화재": 0,
      "DB손해보험": 6070,
      "KB손해보험": 5420,
      "하나손해": 5770,
      "한화손해보험": 6870
    },
    {
      "담보명": "중증질환자암산정특례대상진단",
      "가입금액": "200",
      "메리츠화재": 0,
      "농협손해": 1628,
      "삼성화재": 2266,
      "롯데손해보험": 1976,
      "현대해상화재": 5603,
      "흥국화재": 2381,
      "DB손해보험": 0,
      "KB손해보험": 2387,
      "하나손해": 4408,
      "한화손해보험": 6230
    },
    {
      "담보명": "통합뇌진단비",
      "가입금액": "1000",
      "메리츠화재": 0,
      "농협손해": 0,
      "삼성화재": 0,
      "롯데손해보험": 44900,
      "현대해상화재": 0,
      "흥국화재": 60330,
      "DB손해보험": 0,
      "KB손해보험": 53110,
      "하나손해": 35980,
      "한화손해보험": 46400
    },
    {
      "담보명": "뇌혈관질환진단비",
      "가입금액": "1000",
      "메리츠화재": 19050,
      "농협손해": 16448,
      "삼성화재": 18100,
      "롯데손해보험": 17000,
      "현대해상화재": 19850,
      "흥국화재": 17150,
      "DB손해보험": 19000,
      "KB손해보험": 18890,
      "하나손해": 19440,
      "한화손해보험": 19090
    },
    {
      "담보명": "뇌졸중진단비",
      "가입금액": "1000",
      "메리츠화재": 13220,
      "농협손해": 13377,
      "삼성화재": 13480,
      "롯데손해보험": 13760,
      "현대해상화재": 12350,
      "흥국화재": 16260,
      "DB손해보험": 13290,
      "KB손해보험": 15110,
      "하나손해": 11960,
      "한화손해보험": 15310
    },
    {
      "담보명": "뇌출혈진단비",
      "가입금액": "1000",
      "메리츠화재": 3060,
      "농협손해": 3479,
      "삼성화재": 3100,
      "롯데손해보험": 2860,
      "현대해상화재": 2630,
      "흥국화재": 3320,
      "DB손해보험": 2900,
      "KB손해보험": 3080,
      "하나손해": 2530,
      "한화손해보험": 3180
    },
    {
      "담보명": "뇌혈관질환수술비(매회)",
      "가입금액": "500",
      "메리츠화재": 2115,
      "농협손해": 1920,
      "삼성화재": 0,
      "롯데손해보험": 1600,
      "현대해상화재": 0,
      "흥국화재": 1400,
      "DB손해보험": 2320,
      "KB손해보험": 1170,
      "하나손해": 2465,
      "한화손해보험": 3500
    },
    {
      "담보명": "중증질환자뇌혈관산정특례대상",
      "가입금액": "200",
      "메리츠화재": 1066,
      "농협손해": 580,
      "삼성화재": 796,
      "롯데손해보험": 896,
      "현대해상화재": 946,
      "흥국화재": 850,
      "DB손해보험": 2776,
      "KB손해보험": 682,
      "하나손해": 3528,
      "한화손해보험": 3172
    },
    {
      "담보명": "뇌질환통원일당",
      "가입금액": "2",
      "메리츠화재": 4690,
      "농협손해": 2062,
      "삼성화재": 0,
      "롯데손해보험": 0,
      "현대해상화재": 0,
      "흥국화재": 0,
      "DB손해보험": 2634,
      "KB손해보험": 1710,
      "하나손해": 0,
      "한화손해보험": 3038
    },
    {
      "담보명": "뇌질환통원일당(상급종합병원)",
      "가입금액": "10",
      "메리츠화재": 3350,
      "농협손해": 2580,
      "삼성화재": 0,
      "롯데손해보험": 0,
      "현대해상화재": 0,
      "흥국화재": 0,
      "DB손해보험": 1900,
      "KB손해보험": 2220,
      "하나손해": 0,
      "한화손해보험": 0
    },
    {
      "담보명": "통합심장진단비",
      "가입금액": "1000",
      "메리츠화재": 0,
      "농협손해": 0,
      "삼성화재": 0,
      "롯데손해보험": 49790,
      "현대해상화재": 0,
      "흥국화재": 40260,
      "DB손해보험": 0,
      "KB손해보험": 0,
      "하나손해": 41150,
      "한화손해보험": 64560
    },
    {
      "담보명": "심장질환진단비",
      "가입금액": "100",
      "메리츠화재": 0,
      "농협손해": 4656,
      "삼성화재": 4300,
      "롯데손해보험": 0,
      "현대해상화재": 3957,
      "흥국화재": 3718,
      "DB손해보험": 2999,
      "KB손해보험": 3326,
      "하나손해": 0,
      "한화손해보험": 6084
    },
    {
      "담보명": "허혈성심장질환진단비",
      "가입금액": "1000",
      "메리츠화재": 13310,
      "농협손해": 8439,
      "삼성화재": 11000,
      "롯데손해보험": 10270,
      "현대해상화재": 13500,
      "흥국화재": 11890,
      "DB손해보험": 9760,
      "KB손해보험": 11750,
      "하나손해": 10850,
      "한화손해보험": 14350
    },
    {
      "담보명": "급성심근경색증진단비",
      "가입금액": "1000",
      "메리츠화재": 5050,
      "농협손해": 6691,
      "삼성화재": 5340,
      "롯데손해보험": 3610,
      "현대해상화재": 4620,
      "흥국화재": 5660,
      "DB손해보험": 4510,
      "KB손해보험": 4460,
      "하나손해": 4230,
      "한화손해보험": 7150
    },
    {
      "담보명": "허혈성심장질환수술비(매회)",
      "가입금액": "500",
      "메리츠화재": 3050,
      "농협손해": 2290,
      "삼성화재": 0,
      "롯데손해보험": 2350,
      "현대해상화재": 0,
      "흥국화재": 3700,
      "DB손해보험": 3260,
      "KB손해보험": 3095,
      "하나손해": 3125,
      "한화손해보험": 4035
    },
    {
      "담보명": "중증질환자심장질환산정특례",
      "가입금액": "200",
      "메리츠화재": 2626,
      "농협손해": 1218,
      "삼성화재": 1872,
      "롯데손해보험": 2126,
      "현대해상화재": 2226,
      "흥국화재": 2294,
      "DB손해보험": 4836,
      "KB손해보험": 2248,
      "하나손해": 5978,
      "한화손해보험": 4998
    },
    {
      "담보명": "심장질환통원일당",
      "가입금액": "2",
      "메리츠화재": 4308,
      "농협손해": 1470,
      "삼성화재": 0,
      "롯데손해보험": 0,
      "현대해상화재": 0,
      "흥국화재": 0,
      "DB손해보험": 558,
      "KB손해보험": 326,
      "하나손해": 0,
      "한화손해보험": 2058
    },
    {
      "담보명": "심장질환통원일당(상급종합병원)",
      "가입금액": "10",
      "메리츠화재": 4050,
      "농협손해": 2370,
      "삼성화재": 0,
      "롯데손해보험": 0,
      "현대해상화재": 0,
      "흥국화재": 0,
      "DB손해보험": 620,
      "KB손해보험": 603,
      "하나손해": 0,
      "한화손해보험": 0
    },
    {
      "담보명": "2대질환주요치료비",
      "가입금액": "1000",
      "메리츠화재": 27140,
      "농협손해": 7830,
      "삼성화재": 20780,
      "롯데손해보험": 11150,
      "현대해상화재": 23600,
      "흥국화재": 8230,
      "DB손해보험": 0,
      "KB손해보험": 9470,
      "하나손해": 25020,
      "한화손해보험": 30470
    },
    {
      "담보명": "상급종합병원2대질병치료비",
      "가입금액": "1000",
      "메리츠화재": 12500,
      "농협손해": 0,
      "삼성화재": 9610,
      "롯데손해보험": 5110,
      "현대해상화재": 11580,
      "흥국화재": 0,
      "DB손해보험": 0,
      "KB손해보험": 0,
      "하나손해": 11080,
      "한화손해보험": 14260
    },
    {
      "담보명": "상해수술비",
      "가입금액": "10",
      "메리츠화재": 502,
      "농협손해": 368,
      "삼성화재": 644,
      "롯데손해보험": 592,
      "현대해상화재": 583,
      "흥국화재": 373,
      "DB손해보험": 468,
      "KB손해보험": 414,
      "하나손해": 535,
      "한화손해보험": 511
    },
    {
      "담보명": "질병수술비",
      "가입금액": "10",
      "메리츠화재": 2622,
      "농협손해": 1881,
      "삼성화재": 3324,
      "롯데손해보험": 2600,
      "현대해상화재": 3161,
      "흥국화재": 2845,
      "DB손해보험": 4289,
      "KB손해보험": 2392,
      "하나손해": 2572,
      "한화손해보험": 3819
    },
    {
      "담보명": "N대질병수술비",
      "가입금액": "100",
      "메리츠화재": 18266,
      "농협손해": 19813,
      "삼성화재": 24069,
      "롯데손해보험": 17545,
      "현대해상화재": 13653,
      "흥국화재": 15980,
      "DB손해보험": 16330,
      "KB손해보험": 19460,
      "하나손해": 22550,
      "한화손해보험": 19550
    },
    {
      "담보명": "혈전용해치료비",
      "가입금액": "200",
      "메리츠화재": 624,
      "농협손해": 460,
      "삼성화재": 350,
      "롯데손해보험": 264,
      "현대해상화재": 373,
      "흥국화재": 432,
      "DB손해보험": 390,
      "KB손해보험": 708,
      "하나손해": 350,
      "한화손해보험": 620
    },
    {
      "담보명": "상해(1~5종)수술비 (5종기준)",
      "가입금액": "300",
      "메리츠화재": 885,
      "농협손해": 1019,
      "삼성화재": 1699,
      "롯데손해보험": 870,
      "현대해상화재": 1599,
      "흥국화재": 778,
      "DB손해보험": 1396,
      "KB손해보험": 1002,
      "하나손해": 0,
      "한화손해보험": 1163
    },
    {
      "담보명": "질병(1~5종)수술비 (5종기준)",
      "가입금액": "300",
      "메리츠화재": 12730,
      "농협손해": 12174,
      "삼성화재": 14403,
      "롯데손해보험": 13643,
      "현대해상화재": 15119,
      "흥국화재": 12595,
      "DB손해보험": 7494,
      "KB손해보험": 12063,
      "하나손해": 0,
      "한화손해보험": 15828
    },
    {
      "담보명": "질병입원비",
      "가입금액": "1",
      "메리츠화재": 7531,
      "농협손해": 10543,
      "삼성화재": 7215,
      "롯데손해보험": 9476,
      "현대해상화재": 7153,
      "흥국화재": 10078,
      "DB손해보험": 7888,
      "KB손해보험": 8142,
      "하나손해": 10161,
      "한화손해보험": 13025
    },
    {
      "담보명": "질병중환자실입원비",
      "가입금액": "2",
      "메리츠화재": 76,
      "농협손해": 156,
      "삼성화재": 200,
      "롯데손해보험": 96,
      "현대해상화재": 152,
      "흥국화재": 124,
      "DB손해보험": 132,
      "KB손해보험": 70,
      "하나손해": 148,
      "한화손해보험": 132
    },
    {
      "담보명": "상해입원비",
      "가입금액": "1",
      "메리츠화재": 1015,
      "농협손해": 1638,
      "삼성화재": 1412,
      "롯데손해보험": 1244,
      "현대해상화재": 1315,
      "흥국화재": 3000,
      "DB손해보험": 1210,
      "KB손해보험": 1390,
      "하나손해": 1411,
      "한화손해보험": 2169
    },
    {
      "담보명": "상해중환자실입원비",
      "가입금액": "2",
      "메리츠화재": 134,
      "농협손해": 332,
      "삼성화재": 312,
      "롯데손해보험": 232,
      "현대해상화재": 108,
      "흥국화재": 282,
      "DB손해보험": 196,
      "KB손해보험": 182,
      "하나손해": 206,
      "한화손해보험": 276
    },
    {
      "담보명": "상해입원 1인실 종합병원(상급)",
      "가입금액": "20",
      "메리츠화재": 16,
      "농협손해": 180,
      "삼성화재": 0,
      "롯데손해보험": 100,
      "현대해상화재": 20,
      "흥국화재": 20,
      "DB손해보험": 28,
      "KB손해보험": 20,
      "하나손해": 60,
      "한화손해보험": 6
    },
    {
      "담보명": "질병입원 1인실 종합병원(상급)",
      "가입금액": "20",
      "메리츠화재": 480,
      "농협손해": 2660,
      "삼성화재": 0,
      "롯데손해보험": 1640,
      "현대해상화재": 580,
      "흥국화재": 800,
      "DB손해보험": 1160,
      "KB손해보험": 420,
      "하나손해": 840,
      "한화손해보험": 280
    },
    {
      "담보명": "상해입원 1인실 종합병원",
      "가입금액": "10",
      "메리츠화재": 90,
      "농협손해": 360,
      "삼성화재": 0,
      "롯데손해보험": 220,
      "현대해상화재": 90,
      "흥국화재": 130,
      "DB손해보험": 100,
      "KB손해보험": 90,
      "하나손해": 140,
      "한화손해보험": 220
    },
    {
      "담보명": "질병입원 1인실 종합병원",
      "가입금액": "10",
      "메리츠화재": 770,
      "농협손해": 2780,
      "삼성화재": 0,
      "롯데손해보험": 1830,
      "현대해상화재": 800,
      "흥국화재": 980,
      "DB손해보험": 1370,
      "KB손해보험": 950,
      "하나손해": 1090,
      "한화손해보험": 2340
    },
    {
      "담보명": "상해입원 2~3인 종합병원(상급)",
      "가입금액": "20",
      "메리츠화재": 120,
      "농협손해": 440,
      "삼성화재": 0,
      "롯데손해보험": 280,
      "현대해상화재": 380,
      "흥국화재": 230,
      "DB손해보험": 80,
      "KB손해보험": 220,
      "하나손해": 640,
      "한화손해보험": 160
    },
    {
      "담보명": "질병입원 2~3인 종합병원(상급)",
      "가입금액": "20",
      "메리츠화재": 3460,
      "농협손해": 6740,
      "삼성화재": 0,
      "롯데손해보험": 4520,
      "현대해상화재": 3120,
      "흥국화재": 4240,
      "DB손해보험": 1740,
      "KB손해보험": 3340,
      "하나손해": 9060,
      "한화손해보험": 4140
    },
    {
      "담보명": "상해입원 2~3인 종합병원",
      "가입금액": "10",
      "메리츠화재": 480,
      "농협손해": 950,
      "삼성화재": 0,
      "롯데손해보험": 580,
      "현대해상화재": 870,
      "흥국화재": 1430,
      "DB손해보험": 350,
      "KB손해보험": 630,
      "하나손해": 1390,
      "한화손해보험": 880
    },
    {
      "담보명": "질병입원 2~3인 종합병원",
      "가입금액": "10",
      "메리츠화재": 5420,
      "농협손해": 7400,
      "삼성화재": 0,
      "롯데손해보험": 5020,
      "현대해상화재": 4070,
      "흥국화재": 3700,
      "DB손해보험": 3100,
      "KB손해보험": 4120,
      "하나손해": 10610,
      "한화손해보험": 5910
    },
    {
      "담보명": "간병인상해입원일당(요양병원포함)",
      "가입금액": "5",
      "메리츠화재": 1175,
      "농협손해": 2775,
      "삼성화재": 2425,
      "롯데손해보험": 2170,
      "현대해상화재": 2275,
      "흥국화재": 2610,
      "DB손해보험": 1775,
      "KB손해보험": 1770,
      "하나손해": 2375,
      "한화손해보험": 2918
    },
    {
      "담보명": "간병인질병입원일당(요양병원포함)",
      "가입금액": "5",
      "메리츠화재": 9475,
      "농협손해": 14055,
      "삼성화재": 16580,
      "롯데손해보험": 23130,
      "현대해상화재": 16400,
      "흥국화재": 12650,
      "DB손해보험": 15795,
      "KB손해보험": 13775,
      "하나손해": 24400,
      "한화손해보험": 11520
    },
    {
      "담보명": "상해간호간병통합서비스",
      "가입금액": "10",
      "메리츠화재": 1630,
      "농협손해": 3500,
      "삼성화재": 1180,
      "롯데손해보험": 1050,
      "현대해상화재": 1250,
      "흥국화재": 2710,
      "DB손해보험": 1110,
      "KB손해보험": 1140,
      "하나손해": 1690,
      "한화손해보험": 2410
    },
    {
      "담보명": "질병간호간병통합서비스",
      "가입금액": "10",
      "메리츠화재": 9870,
      "농협손해": 19450,
      "삼성화재": 4720,
      "롯데손해보험": 6910,
      "현대해상화재": 5510,
      "흥국화재": 8680,
      "DB손해보험": 5530,
      "KB손해보험": 5290,
      "하나손해": 9380,
      "한화손해보험": 11580
    },
    {
      "담보명": "통풍진단비",
      "가입금액": "30",
      "메리츠화재": 624,
      "농협손해": 651,
      "삼성화재": 714,
      "롯데손해보험": 0,
      "현대해상화재": 642,
      "흥국화재": 609,
      "DB손해보험": 966,
      "KB손해보험": 504,
      "하나손해": 612,
      "한화손해보험": 690
    },
    {
      "담보명": "대상포진진단비",
      "가입금액": "30",
      "메리츠화재": 1416,
      "농협손해": 1671,
      "삼성화재": 1458,
      "롯데손해보험": 0,
      "현대해상화재": 1122,
      "흥국화재": 1365,
      "DB손해보험": 1464,
      "KB손해보험": 1215,
      "하나손해": 1143,
      "한화손해보험": 1260
    },
    {
      "담보명": "골절진단비(치아파절제외)",
      "가입금액": "10",
      "메리츠화재": 665,
      "농협손해": 712,
      "삼성화재": 670,
      "롯데손해보험": 515,
      "현대해상화재": 742,
      "흥국화재": 646,
      "DB손해보험": 702,
      "KB손해보험": 540,
      "하나손해": 379,
      "한화손해보험": 750
    },
    {
      "담보명": "화상진단비",
      "가입금액": "10",
      "메리츠화재": 64,
      "농협손해": 52,
      "삼성화재": 91,
      "롯데손해보험": 73,
      "현대해상화재": 76,
      "흥국화재": 34,
      "DB손해보험": 75,
      "KB손해보험": 41,
      "하나손해": 55,
      "한화손해보험": 72
    },
    {
      "담보명": "합계",
      "가입금액": "",
      "메리츠화재": 413424,
      "농협손해": 479241,
      "삼성화재": 484362,
      "롯데손해보험": 490632,
      "현대해상화재": 501949,
      "흥국화재": 508833,
      "DB손해보험": 527117,
      "KB손해보험": 567060,
      "하나손해": 607507,
      "한화손해보험": 665854
    }
  ],
  "productData": {
    "메리츠화재": "무)통합간편건강보험(II)2508(통합간편심사형)",
    "농협손해": "무)NH헤아림3.10.10건강보험2504",
    "삼성화재": "무)간편보험 3.10.5 새로고침 100세(2508.3)",
    "롯데손해보험": "무)let:simple 간편 3.10.10 건강보험(2506)",
    "현대해상화재": "무)간편한 3.10.10 건강보험(HI2504)",
    "흥국화재": "무)흥Good 든든한 3N5 간편종합보험(초경증)(25.07)",
    "DB손해보험": "무)나에게 맞춘 더좋은 초경증 간편건강보험2508",
    "KB손해보험": "무)탑클래스3.N.5)초경증간편건강(25.05)",
    "하나손해": "무)하나더넥스트 3N5 간편 건강보험",
    "한화손해보험": "무)더 경증 간편건강보험 2504"
  }
}